[{"nm":"Rest of Michigan","div":"ENC","val":2656.37},{"nm":"Chicago-Naperville-Joliet","div":"ENC","val":2191.84},{"nm":"Battle Creek","div":"ENC","val":2146.86},{"nm":"Grand Rapids-Wyoming","div":"ENC","val":2105.85},{"nm":"Detroit-Warren-Livonia","div":"ENC","val":2011.94},{"nm":"New York-Northern New Jersey-Long Island","div":"NE","val":1468.12},{"nm":"Memphis","div":"ESC","val":1006.82},{"nm":"Lansing-East Lansing","div":"ENC","val":924.51},{"nm":"Canada","div":"LA","val":843.85},{"nm":"China","div":"AS","val":663.35},{"nm":"Niles-Benton Harbor","div":"ENC","val":604.61},{"nm":"Elkhart-Goshen","div":"ENC","val":588.86},{"nm":"Rest of Ohio","div":"ENC","val":569.03},{"nm":"Mexico","div":"LA","val":464.11},{"nm":"Indianapolis","div":"ENC","val":410.67},{"nm":"Holland-Grand Haven","div":"ENC","val":376.93},{"nm":"Jackson","div":"ENC","val":376.64},{"nm":"South Bend-Mishawaka","div":"ENC","val":370.42},{"nm":"Rest of Indiana","div":"ENC","val":349.25},{"nm":"Japan","div":"AS","val":341.69},{"nm":"Milwaukee-Waukesha-West Allis","div":"ENC","val":331.14},{"nm":"Baltimore-Towson","div":"SA","val":309.56},{"nm":"Toledo","div":"ENC","val":305.06},{"nm":"Rest of Wisconsin","div":"ENC","val":282.17},{"nm":"Ann Arbor","div":"ENC","val":236.03},{"nm":"Cleveland-Elyria-Mentor","div":"ENC","val":226.79},{"nm":"Columbus","div":"ENC","val":226.34},{"nm":"Dallas-Fort Worth-Arlington","div":"WSC","val":221.02},{"nm":"Germany","div":"EU","val":220.39},{"nm":"Los Angeles-Long Beach-Santa Ana","div":"PA","val":210.82},{"nm":"Atlanta-Sandy Springs-Marietta","div":"SA","val":203.99},{"nm":"Pittsburgh","div":"NE","val":201.71},{"nm":"Minneapolis-St. Paul-Bloomington","div":"WNC","val":187.3},{"nm":"Fort Wayne","div":"ENC","val":183.25},{"nm":"Philadelphia-Camden-Wilmington","div":"NE","val":170.77},{"nm":"Cincinnati-Middletown","div":"ENC","val":168.61},{"nm":"Remainder of Northern Europe","div":"EU","val":162.07},{"nm":"Houston-Baytown-Sugar Land","div":"WSC","val":161.16},{"nm":"St. Louis","div":"WNC","val":159.99},{"nm":"United Kingdom of Great Britain and Northern Ireland","div":"EU","val":152.93},{"nm":"Remainder of Western Europe","div":"EU","val":152.45},{"nm":"Saginaw-Saginaw Township North","div":"ENC","val":151.74},{"nm":"Madison","div":"ENC","val":148.62},{"nm":"Louisville","div":"ESC","val":146.16},{"nm":"Rest of North Carolina","div":"SA","val":145.48},{"nm":"Muskegon-Norton Shores","div":"ENC","val":136.1},{"nm":"Rest of Illinois","div":"ENC","val":135.57},{"nm":"Flint","div":"ENC","val":133.66},{"nm":"Remainder of Western Asia","div":"AS","val":129.93},{"nm":"Nashville-Davidson--Murfreesboro","div":"ESC","val":129.06},{"nm":"Aggregate of Other Flows","div":"OTHER","val":8505.03}]
